CHANGES.txt
README.txt
bootstrap.py
buildout.cfg
setup.py
src/jarn/__init__.py
src/jarn.jenkins.egg-info/PKG-INFO
src/jarn.jenkins.egg-info/SOURCES.txt
src/jarn.jenkins.egg-info/dependency_links.txt
src/jarn.jenkins.egg-info/entry_points.txt
src/jarn.jenkins.egg-info/namespace_packages.txt
src/jarn.jenkins.egg-info/not-zip-safe
src/jarn.jenkins.egg-info/requires.txt
src/jarn.jenkins.egg-info/top_level.txt
src/jarn/jenkins/__init__.py
src/jarn/jenkins/templates/jenkins.tmpl
src/jarn/jenkins/templates/jetty.xml.tmpl