Metadata-Version: 1.0
Name: jarn.jenkins
Version: 1.0b1
Summary: Buildout recipe for installing a Jenkins instance
Home-page: http://pypi.python.org/pypi/jarn.jenkins
Author: Hanno Schlichting
Author-email: hanno@jarn.com
License: BSD
Keywords: jenkins buildout
Platform: UNKNOWN
Classifier: License :: OSI Approved :: BSD License
Classifier: Framework :: Buildout
Classifier: Framework :: Buildout :: Recipe
